<item name="SMJacket5" class="Item" category="any">
	<params>
		<param name="colorable" value="1"/>
		<param name="droppable" value="1"/>
		<param name="selectable" value="0"/>
		<param name="auto_wear" value="1"/>
		<param name="mass" value="1.5"/>
		<param name="healthMax" value="300.0"/>
		<param name="damage_scale" value="0.1"/>
		<param name="display_name" value="LastShot Military Jacket"/>
		<param name="description" value="LastShot Military Jacket"/>
		<param name="vendor_cost" value="140"/>
	</params>

	<wearable>
		<param name="skin" value="objects/characters/players/male/jacket/military_jacket/military_jacket.skin"/>
		<param name="mtl" value="Objects/characters/players/male/jacket/military_jacket/SM5.mtl"/>
		<param name="slot" value="torso"/>
		<param name="length" value="1"/> <!-- 1 is full length, includes arms -->
	</wearable>

	<geometry>
		<onground name="objects/characters/players/male/jacket/military_jacket/military_jacket_onground.cgf" material="Objects/characters/players/male/jacket/military_jacket/SM5.mtl"/>
	</geometry>	
	
    <protection level="4">
        <environmental>
            <protection_amount type="explosion" percentage="35.0"/>
			<protection_amount type="fire" percentage="50.0"/>
			<protection_amount type="rain" percentage="95.0"/>
			<protection_amount type="humidity" percentage="95.0"/>
			<protection_amount type="rain_acid" percentage="95.0"/>
			<protection_amount type="pool_acid" percentage="95.0"/>
			<protection_amount type="rain_radiation" percentage="95.0"/>
			<protection_amount type="electricity" percentage="95.0"/>
			<protection_amount type="cold" percentage="95.0"/>
			<protection_amount type="heat" percentage="95.0"/>
			<protection_amount type="physical" percentage="95.0"/>
        </environmental>
			<protectBodyPart name="shoulderLeft"> <!-- Use valid bodyparts defined in Libs/BodyDamage/BodyParts_*.xml -->
			<protection_amount hit_type="default" percentage="45.0"/> <!-- Default damage reduction of 75% unless specified below -->
			<protection_amount hit_type="blunt" percentage="85.0"/>
			<protection_amount hit_type="melee" percentage="85.0"/>
			<protection_amount hit_type="ammo_357" percentage="30.0"/>
			<protection_amount hit_type="ammo_44M" percentage="15.0"/>
			<protection_amount hit_type="ammo_9mm" percentage="40.0"/>
			<protection_amount hit_type="ammo_10mm" percentage="40.0"/>
			<protection_amount hit_type="ammo_acp_45" percentage="40.0"/>
			<protection_amount hit_type="ammo_308" percentage="25.0"/>
			<protection_amount hit_type="ammo_7_62x39" percentage="25.0"/>
			<protection_amount hit_type="ammo_7_62x51" percentage="25.0"/>
			<protection_amount hit_type="ammo_5_45x39" percentage="25.0"/>
			<protection_amount hit_type="ammo_5_56x45" percentage="30.0"/>
			<protection_amount hit_type="ammo_223" percentage="25.0"/>
			<protection_amount hit_type="ammo_5_70x28" percentage="30.0"/> 
			<protection_amount hit_type="ammo_50cal" percentage="25.0"/>
			<protection_amount hit_type="ammo_50calx" percentage="25.0"/>
			<protection_amount hit_type="ammo_7_62x39_Venom" percentage="25.0"/>
			<protection_amount hit_type="ammo_5_56x77" percentage="25.0"/>
		</protectBodyPart>
		<protectBodyPart name="shoulderRight"> <!-- Use valid bodyparts defined in Libs/BodyDamage/BodyParts_*.xml -->
			<protection_amount hit_type="default" percentage="45.0"/> <!-- Default damage reduction of 75% unless specified below -->
			<protection_amount hit_type="blunt" percentage="85.0"/>
			<protection_amount hit_type="melee" percentage="85.0"/>
			<protection_amount hit_type="ammo_357" percentage="30.0"/>
			<protection_amount hit_type="ammo_44M" percentage="15.0"/>
			<protection_amount hit_type="ammo_9mm" percentage="40.0"/>
			<protection_amount hit_type="ammo_10mm" percentage="40.0"/>
			<protection_amount hit_type="ammo_acp_45" percentage="40.0"/>
			<protection_amount hit_type="ammo_308" percentage="25.0"/>
			<protection_amount hit_type="ammo_7_62x39" percentage="25.0"/>
			<protection_amount hit_type="ammo_7_62x51" percentage="25.0"/>
			<protection_amount hit_type="ammo_5_45x39" percentage="25.0"/>
			<protection_amount hit_type="ammo_5_56x45" percentage="30.0"/>
			<protection_amount hit_type="ammo_223" percentage="25.0"/>
			<protection_amount hit_type="ammo_5_70x28" percentage="30.0"/> 
			<protection_amount hit_type="ammo_50cal" percentage="25.0"/>
			<protection_amount hit_type="ammo_50calx" percentage="25.0"/>
			<protection_amount hit_type="ammo_7_62x39_Venom" percentage="25.0"/>
			<protection_amount hit_type="ammo_5_56x77" percentage="25.0"/>
		</protectBodyPart>
	</protection>

	<usable>
		<param name="action" value="craft"/>
		<param name="param" value="Rags"/>
		<param name="soundUsed" value="Play_fabric_tear"/>
	</usable>

	<storage>
		<locations>
			<location category="any"/>
			<location category="torso"/>
		</locations>
		<types>
			<type category="any" capacity="10"/>
		</types>
	</storage>


	<steam>
		<param name="tags" value="Category:Clothing;Slot:Torso"/>
		<param name="icon_url" value="http://miscreatedgame.com/shots/item_images/MilitaryJacketBlack_200.png?crc=C627F6CD"/>
		<param name="store_hidden" value="0"/>
		<param name="amcoins" value="3"/>
		<param name="tradable" value="0"/>
		<param name="name_color" value="FF001E"/>
		<param name="itemdefid" value="40689"/>
		<param name="marketable" value="0"/>
		<param name="store_tags" value="Category:Clothing;Slot:Torso"/>
		<param name="background_color" value="2A2A2A"/>
		<param name="hidden" value="0"/>
		<param name="icon_url_large" value="http://miscreatedgame.com/shots/item_images/MilitaryJacketBlack_2048.png?crc=C627F6CD"/>
	</steam>
</item>